botonVariocolor/componente.py
botonVariocolor/componente_demo.py
botonVariocolor-0.1.dist-info/LICENSE.txt
botonVariocolor-0.1.dist-info/METADATA
botonVariocolor-0.1.dist-info/WHEEL
botonVariocolor-0.1.dist-info/top_level.txt
botonVariocolor-0.1.dist-info/RECORD
