Metadata-Version: 2.1
Name: botonVariocolor
Version: 0.1
Summary: Componente que varía de color un botón con una paleta de color
Home-page: https://github.com/danielmera2912/botonVariocolor
Author: danielmera2912
Author-email: dmersac2912@g.educaand.es
License: MIT
Download-URL: https://github.com/danielmera2912/botonVariocolor/archive/refs/tags/0.1.tar.gz
Keywords: variocolor
Platform: UNKNOWN
Classifier: Programming Language :: Python
Classifier: Programming Language :: Python :: 2.7
Classifier: Programming Language :: Python :: 3.3
Classifier: Programming Language :: Python :: 3.4
Classifier: Programming Language :: Python :: 3.5
Classifier: Programming Language :: Python :: 3.6
Classifier: Programming Language :: Python :: 3.7
License-File: LICENSE.txt
